Metadata-Version: 2.1
Name: soldai-utils-maxsob86
Version: 0.0.1
Summary: Soldai utilities for machine learning and text processing
Home-page: https://github.com/SoldAI/sutil
Author: Soldai Research
Author-email: mcampos@soldai.com
License: UNKNOWN
Platform: UNKNOWN
Classifier: Programming Language :: Python :: 3
Classifier: License :: OSI Approved :: MIT License
Classifier: Operating System :: OS Independent
Requires-Python: >=3.6
